README.md
setup.py
recbench/__init__.py
recbench.egg-info/PKG-INFO
recbench.egg-info/SOURCES.txt
recbench.egg-info/dependency_links.txt
recbench.egg-info/top_level.txt