Metadata-Version: 2.1
Name: recbench
Version: 0.0.1
Summary: Benchmarking Recabilities for Large Language Models
Home-page: https://github.com/Jyonn/RecBench
Author: Jyonn Liu
Author-email: i@6-79.cn
License: MIT Licence
Keywords: recommendation,benchmark
Platform: any
